main.py
whattimeisit_mcp-0.1.0.dist-info/licenses/LICENSE
whattimeisit_mcp-0.1.0.dist-info/METADATA
whattimeisit_mcp-0.1.0.dist-info/WHEEL
whattimeisit_mcp-0.1.0.dist-info/top_level.txt
whattimeisit_mcp-0.1.0.dist-info/RECORD
